{
    "backend": "django",
    "db_name": "",
    "db_pass": "",
    "db_type": "mysql",
    "db_user": "",
    "dbms": "1",
    "description": "generated product",
    "design": "material-dashboard",
    "docker": "1",
    "err_code": 0,
    "frontend": "",
    "heroku": "0",
    "pattern": "mvc",
    "pro": "0",
    "task_id": "ae7ac96a-3f37-471e-98f5-41c7a09aa268",
    "task_info": "Upload Sources [0%] - 392 files",
    "task_output": "ae7ac96a-3f37-471e-98f5-41c7a09aa268.zip",
    "task_result": "SUCCESS",
    "task_state": "RUNNING",
    "task_ts_end": "2023-04-01-10-24-34",
    "task_ts_start": "2023-04-01-10-24-32"
}